http_server_pro/__init__.py
http_server_pro/__version__.py
http_server_pro/class_handler.py
http_server_pro/dependencies_checker.py
http_server_pro/handler_fixed.py
http_server_pro/main.py
http_server_pro/main_secondry.py
http_server_pro/useful_fn.py
http_server_pro-7.7.5.dist-info/LICENSE
http_server_pro-7.7.5.dist-info/METADATA
http_server_pro-7.7.5.dist-info/WHEEL
http_server_pro-7.7.5.dist-info/entry_points.txt
http_server_pro-7.7.5.dist-info/top_level.txt
http_server_pro-7.7.5.dist-info/RECORD
