Metadata-Version: 2.1
Name: http_server_pro
Version: 7.7.5
Summary: A Local HTTP File Server with ngrok & QR support
Home-page: https://github.com/kdiitg/http_server_pro
Author: Kuldeep Singh
License: MIT
Project-URL: Documentation, https://github.com/kdiitg/http_server_pro
Project-URL: Source, https://github.com/kdiitg/http_server_pro
Project-URL: Bug Tracker, https://github.com/kdiitg/http_server_pro/issues
Keywords: http server local file-sharing ngrok QR tkinter gui
Classifier: Programming Language :: Python :: 3
Classifier: License :: OSI Approved :: MIT License
Classifier: Operating System :: OS Independent
Classifier: Topic :: Internet :: File Transfer Protocol (FTP)
Classifier: Topic :: Utilities
Requires-Python: >=3.7
License-File: LICENSE
Requires-Dist: Pillow ~=11.2.1
Requires-Dist: qrcode ~=8.2
Requires-Dist: requests ~=2.32.4
